sociallimits/__init__.py
sociallimits-1.0.0.dist-info/LICENSE
sociallimits-1.0.0.dist-info/METADATA
sociallimits-1.0.0.dist-info/WHEEL
sociallimits-1.0.0.dist-info/top_level.txt
sociallimits-1.0.0.dist-info/RECORD
